README
setup.py
PySpotCam/SpotCamCStructure.py
PySpotCam/SpotCamConstant.py
PySpotCam/SpotCamEnum.py
PySpotCam/SpotCamFunction.py
PySpotCam/SpotCamTuple.py
PySpotCam/SpotValue.py
PySpotCam/SpotValueClassDefinition.py
PySpotCam/__init__.py
PySpotCam/spot.py
PySpotCam.egg-info/PKG-INFO
PySpotCam.egg-info/SOURCES.txt
PySpotCam.egg-info/dependency_links.txt
PySpotCam.egg-info/top_level.txt