Metadata-Version: 1.0
Name: PySpotCam
Version: 1.0.0
Summary: Interface to the SpotCam driver.
Home-page: http://packages.python.org/PySpotCam/
Author: Pierre Cladé
Author-email: pierre.clade@spectro.jussieu.fr
License: This software can be used under one of the following two licenses: (1) The BSD license. (2) Any other license, as long as it is obtained from the original author.
Keywords: SpotCam,SPOT Imaging Solutions,Camera
Platform: UNKNOWN
Classifier: Development Status :: 4 - Beta
Classifier: Intended Audience :: Developers
Classifier: Intended Audience :: Education
Classifier: Intended Audience :: Other Audience
Classifier: Intended Audience :: Science/Research
Classifier: License :: OSI Approved :: BSD License
Classifier: Programming Language :: Python
Classifier: Topic :: Scientific/Engineering
Classifier: Topic :: Scientific/Engineering :: Physics
Classifier: Topic :: Software Development
Classifier: Topic :: Software Development :: Libraries
Classifier: Topic :: Software Development :: Libraries :: Python Modules
